omnieq/__init__.py
omnieq/client.py
omnieq/httpapi.py
omnieq/utils/__init__.py
omnieq/utils/pd_funcs.py
omnieq/utils/symbol_funcs.py
omnieq_api-1.0.0.dist-info/METADATA
omnieq_api-1.0.0.dist-info/WHEEL
omnieq_api-1.0.0.dist-info/top_level.txt
omnieq_api-1.0.0.dist-info/RECORD
