Metadata-Version: 2.1
Name: omnieq-api
Version: 1.0.0
Summary: OmniEQ API wrapper
Home-page: https://github.com/eklingen88/omnieq-python-api
Author: Eric M. Klingensmith
Author-email: eric.m.klingensmith@gmail.com
License: UNKNOWN
Platform: UNKNOWN
Classifier: Programming Language :: Python :: 3
Classifier: License :: OSI Approved :: MIT License
Classifier: Operating System :: OS Independent
Requires-Python: >=3.6
Requires-Dist: diskcache
Requires-Dist: ratelimit
Requires-Dist: requests
Requires-Dist: joblib
Requires-Dist: pandas
Requires-Dist: numpy
